qpytexi/__init__.py
qpytexi/cli.py
qpytexi/compiler.py
qpytexi/processor.py
qpytexi/templates/base_qtex_template.tex
qpytexi-0.1.7.dist-info/METADATA
qpytexi-0.1.7.dist-info/WHEEL
qpytexi-0.1.7.dist-info/entry_points.txt
qpytexi-0.1.7.dist-info/licenses/LICENSE
qpytexi-0.1.7.dist-info/RECORD
