Metadata-Version: 2.4
Name: qpytexi
Version: 0.1.7
Summary: A Python package for generating LaTeX documents with Python integration
License: MIT
License-File: LICENSE
Keywords: latex,python,education,quiz,template,tex
Author: Khris Griffis, Ph.D.
Author-email: khris.griffis.phd@gmail.com
Maintainer: Khris Griffis, Ph.D.
Maintainer-email: khris.griffis.phd@gmail.com
Requires-Python: >=3.11,<4.0
Classifier: Development Status :: 4 - Beta
Classifier: Intended Audience :: Education
Classifier: License :: OSI Approved :: MIT License
Classifier: Operating System :: OS Independent
Classifier: Programming Language :: Python :: 3
Classifier: Programming Language :: Python :: 3.11
Classifier: Programming Language :: Python :: 3.12
Classifier: Programming Language :: Python :: 3.13
Classifier: Programming Language :: Python :: 3.14
Classifier: Topic :: Education :: Testing
Classifier: Topic :: Text Processing :: Markup :: LaTeX
Requires-Dist: matplotlib
Requires-Dist: numpy
Project-URL: Bug Tracker, https://github.com/Khlick/qtex/issues
Project-URL: Documentation, https://github.com/Khlick/qtex#readme
Project-URL: Homepage, https://github.com/Khlick/qtex
Project-URL: Repository, https://github.com/Khlick/qtex
